PolibaseAutomationService/__init__.py
PolibaseAutomationService/__main__.py
PolibaseAutomationService/const.py
PolibaseAutomationService/service.py
pih_plb_auto-0.15.dist-info/METADATA
pih_plb_auto-0.15.dist-info/WHEEL
pih_plb_auto-0.15.dist-info/entry_points.txt
pih_plb_auto-0.15.dist-info/top_level.txt
pih_plb_auto-0.15.dist-info/RECORD
